sportradar/BeachVolleyball.py
sportradar/Cricket.py
sportradar/Darts.py
sportradar/Golf.py
sportradar/MLB.py
sportradar/NASCAR.py
sportradar/NBA.py
sportradar/NCAAMB.py
sportradar/NFL.py
sportradar/NHL.py
sportradar/Rugby.py
sportradar/Soccer.py
sportradar/Tennis.py
sportradar/WNBA.py
sportradar/__init__.py
sportradar/api.py
sportradar/eSportsDota2.py
sportradar/eSportsLoL.py
sportradar-1.6.0.dist-info/LICENSE
sportradar-1.6.0.dist-info/METADATA
sportradar-1.6.0.dist-info/WHEEL
sportradar-1.6.0.dist-info/top_level.txt
sportradar-1.6.0.dist-info/RECORD
