Metadata-Version: 2.1
Name: sportradar
Version: 1.6.0
Summary: A Python wrapper for the Sportradar APIs
Home-page: https://github.com/johnwmillr/SportradarAPIs
Author: John W. Miller
License: MIT
Keywords: sportsradar API sports basketball NBA football NFL soccer
Platform: UNKNOWN
Classifier: Topic :: Software Development :: Libraries
Classifier: Operating System :: OS Independent
Classifier: Programming Language :: Python
Classifier: Programming Language :: Python :: 3
Requires-Python: >=3.*
Requires-Dist: requests
